{"northamerica": {"grammar": ["atla1278", "indo1319", "tsim1258", "eski1264", "yoku1255", "mixe1284", "coch1271", "None", "waka1280", "maya1287", "miwo1274", "maid1262", "toto1251", "otom1299", "huav1256", "kiow1265", "coos1248", "araw1281", "pomo1273", "yuki1242", "shas1238", "musk1252", "utoa1244", "siou1252", "sali1255", "kere1287", "atha1245", "chim1311", "misu1242", "algi1248", "chib1249", "iroq1247"], "grammarsketch": ["chin1490", "pala1350", "tequ1244", "chum1262", "saha1239", "jica1245", "kala1402", "xinc1237", "cadd1255"]}, "pacific": {"grammar": ["sout2948", "nucl1709", "indo1319", "aust1305", "bord1247", "east2503", "manu1261", "koia1260", "geel1240", "None", "sepi1257", "timo1261", "nort2923", "nimb1257", "goil1242", "japo1237", "kiwa1251", "lowe1437", "hata1242", "kwom1263", "monu1249", "skoo1245", "nduu1242", "nucl1580", "anga1289", "nucl1708", "pama1250", "tebe1251", "aust1307"], "grammarsketch": ["sout1516", "piaw1238", "taul1250", "suki1244", "mair1253", "kolo1268", "west1493", "tura1263", "east2433", "pauw1244", "bain1263", "kwer1242", "sent1261", "amto1249", "yare1250", "lake1255", "grea1241", "west2604", "daga1274", "toro1256", "paho1240", "anim1240", "left1242", "kamu1264", "bosa1245", "mail1249", "momb1255", "yawa1259", "yuat1252", "east1459", "east2499", "nort2933", "soma1242", "more1255", "bula1259", "inan1242"]}, "southamerica": {"grammar": ["indo1319", "chon1288", "boro1281", "cahu1265", "nucl1710", "None", "guai1249", "barb1265", "zamu1243", "huit1251", "quec1387", "yano1268", "tupi1275", "choc1280", "araw1282", "ayma1253", "araw1281", "jodi1234", "cari1283", "jiva1245", "tuca1253", "leng1261", "namb1299", "mata1289", "chib1249", "pano1259", "aust1307"], "grammarsketch": ["kari1254", "kawe1237", "arau1255", "peba1241", "guah1252", "zapa1251", "huar1251", "chap1271", "kaku1242", "bora1262"]}, "australia": {"grammar": ["west2434", "mang1423", "indo1319", "jarr1235", "limi1242", "buna1274", "east2374", "tang1340", "None", "mani1293", "worr1236", "mirn1241", "nort1547", "pama1250"], "grammarsketch": ["gunw1250", "giim1238", "nyul1248", "iwai1246"]}, "eurasia": {"grammar": ["kart1248", "indo1319", "taik1256", "aust1305", "eski1264", "afro1255", "ainu1252", "hmon1336", "hurr1239", "drav1251", "None", "abkh1242", "ural1272", "japo1237", "turk1311", "tung1282", "sino1245", "nakh1245", "mong1329", "aust1307"], "grammarsketch": ["chuk1271", "grea1241", "jara1244"]}, "africa": {"grammar": ["atla1278", "indo1319", "ijoi1239", "khoe1240", "nubi1251", "afro1255", "kuli1252", "daju1249", "nyim1244", "None", "cent2225", "heib1242", "gumu1250", "surm1244", "sout2845", "saha1256", "kxaa1236", "maoo1243", "dogo1299", "maba1274", "dizo1235", "nilo1247", "gong1255", "song1307", "narr1279", "mand1469", "aust1307"], "grammarsketch": ["tama1329", "kres1240", "tuuu1241", "koma1264", "rash1249", "katl1246", "kadu1256"]}}